{
"type": "FeatureCollection",
"name": "polyclinic",
"crs": { "type": "name", "properties": { "name": "urn:ogc:def:crs:OGC:1.3:CRS84" } },
"features": [
{ "type": "Feature", "properties": { "fid": 2, "id": null, "amenity": "polyclinic", "contact": null, "phone": null, "vk": null, "name": "Тайцкая амбулатория", "capacity": "250" }, "geometry": { "type": "Point", "coordinates": [ 30.110006113235688, 59.663617482169585 ] } }
]
}
