{
"type": "FeatureCollection",
"name": "school",
"crs": { "type": "name", "properties": { "name": "urn:ogc:def:crs:OGC:1.3:CRS84" } },
"features": [
{ "type": "Feature", "properties": { "fid": 1, "id": null, "amenity": "school", "contact": null, "phone": null, "vk": null, "name": "МБОУ \"Таицкая СОШ\" ", "capacity": 750.0 }, "geometry": { "type": "Point", "coordinates": [ 30.105963728146115, 59.660609116906869 ] } }
]
}
